zenserp/__init__.py
zenserp/client.py
zenserp-0.2.dist-info/METADATA
zenserp-0.2.dist-info/WHEEL
zenserp-0.2.dist-info/top_level.txt
zenserp-0.2.dist-info/RECORD
